Compiled from "CustomDoorRenderer.java"
public class net.malisis.doors.renderer.CustomDoorRenderer extends net.malisis.doors.renderer.DoorRenderer {
  public static net.malisis.doors.renderer.CustomDoorRenderer instance;

  private net.minecraft.block.state.IBlockState frame;

  private net.minecraft.block.state.IBlockState top;

  private net.minecraft.block.state.IBlockState bottom;

  private float width;

  public net.malisis.doors.renderer.CustomDoorRenderer();
    Code:
       0: aload_0
       1: iconst_0
       2: invokespecial #18                 // Method net/malisis/doors/renderer/DoorRenderer."<init>":(Z)V
       5: aload_0
       6: ldc           #20                 // class net/malisis/doors/tileentity/CustomDoorTileEntity
       8: invokevirtual #24                 // Method registerFor:(Ljava/lang/Class;)V
      11: return

  protected void initialize();
    Code:
       0: aload_0
       1: ldc           #27                 // float 0.125f
       3: putfield      #29                 // Field width:F
       6: new           #31                 // class net/malisis/core/renderer/element/shape/Cube
       9: dup
      10: invokespecial #33                 // Method net/malisis/core/renderer/element/shape/Cube."<init>":()V
      13: aload_0
      14: getfield      #29                 // Field width:F
      17: fconst_1
      18: ldc           #34                 // float 0.1875f
      20: invokevirtual #38                 // Method net/malisis/core/renderer/element/shape/Cube.setSize:(FFF)Lnet/malisis/core/renderer/element/Shape;
      23: astore_1
      24: new           #40                 // class net/malisis/core/renderer/element/Shape
      27: dup
      28: aload_1
      29: invokespecial #43                 // Method net/malisis/core/renderer/element/Shape."<init>":(Lnet/malisis/core/renderer/element/Shape;)V
      32: astore_2
      33: aload_2
      34: fconst_1
      35: aload_0
      36: getfield      #29                 // Field width:F
      39: fsub
      40: fconst_0
      41: fconst_0
      42: invokevirtual #47                 // Method net/malisis/core/renderer/element/Shape.translate:(FFF)V
      45: new           #40                 // class net/malisis/core/renderer/element/Shape
      48: dup
      49: iconst_4
      50: anewarray     #49                 // class net/malisis/core/renderer/element/Face
      53: dup
      54: iconst_0
      55: new           #51                 // class net/malisis/core/renderer/element/face/NorthFace
      58: dup
      59: invokespecial #52                 // Method net/malisis/core/renderer/element/face/NorthFace."<init>":()V
      62: aastore
      63: dup
      64: iconst_1
      65: new           #54                 // class net/malisis/core/renderer/element/face/SouthFace
      68: dup
      69: invokespecial #55                 // Method net/malisis/core/renderer/element/face/SouthFace."<init>":()V
      72: aastore
      73: dup
      74: iconst_2
      75: new           #57                 // class net/malisis/core/renderer/element/face/TopFace
      78: dup
      79: invokespecial #58                 // Method net/malisis/core/renderer/element/face/TopFace."<init>":()V
      82: aastore
      83: dup
      84: iconst_3
      85: new           #60                 // class net/malisis/core/renderer/element/face/BottomFace
      88: dup
      89: invokespecial #61                 // Method net/malisis/core/renderer/element/face/BottomFace."<init>":()V
      92: aastore
      93: invokespecial #64                 // Method net/malisis/core/renderer/element/Shape."<init>":([Lnet/malisis/core/renderer/element/Face;)V
      96: astore_3
      97: aload_3
      98: fconst_1
      99: fconst_2
     100: aload_0
     101: getfield      #29                 // Field width:F
     104: fmul
     105: fsub
     106: aload_0
     107: getfield      #29                 // Field width:F
     110: ldc           #34                 // float 0.1875f
     112: invokevirtual #65                 // Method net/malisis/core/renderer/element/Shape.setSize:(FFF)Lnet/malisis/core/renderer/element/Shape;
     115: pop
     116: aload_3
     117: aload_0
     118: getfield      #29                 // Field width:F
     121: fconst_0
     122: fconst_0
     123: invokevirtual #47                 // Method net/malisis/core/renderer/element/Shape.translate:(FFF)V
     126: iconst_3
     127: anewarray     #40                 // class net/malisis/core/renderer/element/Shape
     130: dup
     131: iconst_0
     132: aload_1
     133: aastore
     134: dup
     135: iconst_1
     136: aload_2
     137: aastore
     138: dup
     139: iconst_2
     140: aload_3
     141: aastore
     142: invokestatic  #69                 // Method net/malisis/core/renderer/element/Shape.fromShapes:([Lnet/malisis/core/renderer/element/Shape;)Lnet/malisis/core/renderer/element/Shape;
     145: astore        4
     147: aload         4
     149: fconst_1
     150: fconst_1
     151: ldc           #70                 // float 0.995f
     153: invokevirtual #73                 // Method net/malisis/core/renderer/element/Shape.scale:(FFF)V
     156: aload         4
     158: invokevirtual #77                 // Method net/malisis/core/renderer/element/Shape.applyMatrix:()Lnet/malisis/core/renderer/element/Shape;
     161: pop
     162: new           #40                 // class net/malisis/core/renderer/element/Shape
     165: dup
     166: iconst_3
     167: anewarray     #49                 // class net/malisis/core/renderer/element/Face
     170: dup
     171: iconst_0
     172: new           #54                 // class net/malisis/core/renderer/element/face/SouthFace
     175: dup
     176: invokespecial #55                 // Method net/malisis/core/renderer/element/face/SouthFace."<init>":()V
     179: aastore
     180: dup
     181: iconst_1
     182: new           #51                 // class net/malisis/core/renderer/element/face/NorthFace
     185: dup
     186: invokespecial #52                 // Method net/malisis/core/renderer/element/face/NorthFace."<init>":()V
     189: aastore
     190: dup
     191: iconst_2
     192: new           #57                 // class net/malisis/core/renderer/element/face/TopFace
     195: dup
     196: invokespecial #58                 // Method net/malisis/core/renderer/element/face/TopFace."<init>":()V
     199: aastore
     200: invokespecial #64                 // Method net/malisis/core/renderer/element/Shape."<init>":([Lnet/malisis/core/renderer/element/Face;)V
     203: astore        5
     205: aload         5
     207: fconst_1
     208: fconst_2
     209: aload_0
     210: getfield      #29                 // Field width:F
     213: fmul
     214: fsub
     215: fconst_1
     216: aload_0
     217: getfield      #29                 // Field width:F
     220: fsub
     221: ldc           #78                 // float 0.112500004f
     223: invokevirtual #65                 // Method net/malisis/core/renderer/element/Shape.setSize:(FFF)Lnet/malisis/core/renderer/element/Shape;
     226: aload_0
     227: getfield      #29                 // Field width:F
     230: aload_0
     231: getfield      #29                 // Field width:F
     234: ldc           #79                 // float 0.0375f
     236: invokevirtual #47                 // Method net/malisis/core/renderer/element/Shape.translate:(FFF)V
     239: aload         5
     241: invokevirtual #77                 // Method net/malisis/core/renderer/element/Shape.applyMatrix:()Lnet/malisis/core/renderer/element/Shape;
     244: pop
     245: new           #40                 // class net/malisis/core/renderer/element/Shape
     248: dup
     249: invokespecial #80                 // Method net/malisis/core/renderer/element/Shape."<init>":()V
     252: astore        6
     254: aload         6
     256: aload         4
     258: invokevirtual #84                 // Method net/malisis/core/renderer/element/Shape.getFaces:()[Lnet/malisis/core/renderer/element/Face;
     261: ldc           #85                 // String frame
     263: invokevirtual #89                 // Method net/malisis/core/renderer/element/Shape.addFaces:([Lnet/malisis/core/renderer/element/Face;Ljava/lang/String;)Lnet/malisis/core/renderer/element/Shape;
     266: pop
     267: aload         6
     269: aload         5
     271: invokevirtual #84                 // Method net/malisis/core/renderer/element/Shape.getFaces:()[Lnet/malisis/core/renderer/element/Face;
     274: ldc           #91                 // String material
     276: invokevirtual #89                 // Method net/malisis/core/renderer/element/Shape.addFaces:([Lnet/malisis/core/renderer/element/Face;Ljava/lang/String;)Lnet/malisis/core/renderer/element/Shape;
     279: pop
     280: aload         6
     282: invokevirtual #94                 // Method net/malisis/core/renderer/element/Shape.interpolateUV:()Lnet/malisis/core/renderer/element/Shape;
     285: pop
     286: aload         6
     288: invokevirtual #97                 // Method net/malisis/core/renderer/element/Shape.storeState:()Lnet/malisis/core/renderer/element/Shape;
     291: pop
     292: new           #40                 // class net/malisis/core/renderer/element/Shape
     295: dup
     296: aload_1
     297: invokespecial #43                 // Method net/malisis/core/renderer/element/Shape."<init>":(Lnet/malisis/core/renderer/element/Shape;)V
     300: astore_1
     301: new           #40                 // class net/malisis/core/renderer/element/Shape
     304: dup
     305: aload_2
     306: invokespecial #43                 // Method net/malisis/core/renderer/element/Shape."<init>":(Lnet/malisis/core/renderer/element/Shape;)V
     309: astore_2
     310: new           #40                 // class net/malisis/core/renderer/element/Shape
     313: dup
     314: aload_3
     315: invokespecial #43                 // Method net/malisis/core/renderer/element/Shape."<init>":(Lnet/malisis/core/renderer/element/Shape;)V
     318: astore_3
     319: aload_3
     320: fconst_0
     321: fconst_1
     322: aload_0
     323: getfield      #29                 // Field width:F
     326: fsub
     327: fconst_0
     328: invokevirtual #47                 // Method net/malisis/core/renderer/element/Shape.translate:(FFF)V
     331: iconst_3
     332: anewarray     #40                 // class net/malisis/core/renderer/element/Shape
     335: dup
     336: iconst_0
     337: aload_1
     338: aastore
     339: dup
     340: iconst_1
     341: aload_2
     342: aastore
     343: dup
     344: iconst_2
     345: aload_3
     346: aastore
     347: invokestatic  #69                 // Method net/malisis/core/renderer/element/Shape.fromShapes:([Lnet/malisis/core/renderer/element/Shape;)Lnet/malisis/core/renderer/element/Shape;
     350: astore        4
     352: aload         4
     354: fconst_1
     355: fconst_1
     356: ldc           #70                 // float 0.995f
     358: invokevirtual #73                 // Method net/malisis/core/renderer/element/Shape.scale:(FFF)V
     361: aload         4
     363: invokevirtual #77                 // Method net/malisis/core/renderer/element/Shape.applyMatrix:()Lnet/malisis/core/renderer/element/Shape;
     366: pop
     367: new           #40                 // class net/malisis/core/renderer/element/Shape
     370: dup
     371: aload         5
     373: invokespecial #43                 // Method net/malisis/core/renderer/element/Shape."<init>":(Lnet/malisis/core/renderer/element/Shape;)V
     376: astore        5
     378: aload         5
     380: fconst_0
     381: aload_0
     382: getfield      #29                 // Field width:F
     385: fneg
     386: fconst_0
     387: invokevirtual #47                 // Method net/malisis/core/renderer/element/Shape.translate:(FFF)V
     390: aload         5
     392: invokevirtual #77                 // Method net/malisis/core/renderer/element/Shape.applyMatrix:()Lnet/malisis/core/renderer/element/Shape;
     395: pop
     396: new           #40                 // class net/malisis/core/renderer/element/Shape
     399: dup
     400: invokespecial #80                 // Method net/malisis/core/renderer/element/Shape."<init>":()V
     403: astore        7
     405: aload         7
     407: aload         4
     409: invokevirtual #84                 // Method net/malisis/core/renderer/element/Shape.getFaces:()[Lnet/malisis/core/renderer/element/Face;
     412: ldc           #85                 // String frame
     414: invokevirtual #89                 // Method net/malisis/core/renderer/element/Shape.addFaces:([Lnet/malisis/core/renderer/element/Face;Ljava/lang/String;)Lnet/malisis/core/renderer/element/Shape;
     417: pop
     418: aload         7
     420: aload         5
     422: invokevirtual #84                 // Method net/malisis/core/renderer/element/Shape.getFaces:()[Lnet/malisis/core/renderer/element/Face;
     425: ldc           #91                 // String material
     427: invokevirtual #89                 // Method net/malisis/core/renderer/element/Shape.addFaces:([Lnet/malisis/core/renderer/element/Face;Ljava/lang/String;)Lnet/malisis/core/renderer/element/Shape;
     430: pop
     431: aload         7
     433: fconst_0
     434: fconst_1
     435: fconst_0
     436: invokevirtual #47                 // Method net/malisis/core/renderer/element/Shape.translate:(FFF)V
     439: aload         7
     441: invokevirtual #94                 // Method net/malisis/core/renderer/element/Shape.interpolateUV:()Lnet/malisis/core/renderer/element/Shape;
     444: pop
     445: aload         7
     447: invokevirtual #97                 // Method net/malisis/core/renderer/element/Shape.storeState:()Lnet/malisis/core/renderer/element/Shape;
     450: pop
     451: aload_0
     452: new           #99                 // class net/malisis/core/renderer/model/MalisisModel
     455: dup
     456: invokespecial #100                // Method net/malisis/core/renderer/model/MalisisModel."<init>":()V
     459: putfield      #104                // Field model:Lnet/malisis/core/renderer/model/MalisisModel;
     462: aload_0
     463: getfield      #104                // Field model:Lnet/malisis/core/renderer/model/MalisisModel;
     466: ldc           #105                // String bottom
     468: aload         6
     470: invokevirtual #109                // Method net/malisis/core/renderer/model/MalisisModel.addShape:(Ljava/lang/String;Lnet/malisis/core/renderer/element/Shape;)V
     473: aload_0
     474: getfield      #104                // Field model:Lnet/malisis/core/renderer/model/MalisisModel;
     477: ldc           #110                // String top
     479: aload         7
     481: invokevirtual #109                // Method net/malisis/core/renderer/model/MalisisModel.addShape:(Ljava/lang/String;Lnet/malisis/core/renderer/element/Shape;)V
     484: aload_0
     485: getfield      #104                // Field model:Lnet/malisis/core/renderer/model/MalisisModel;
     488: invokevirtual #112                // Method net/malisis/core/renderer/model/MalisisModel.storeState:()V
     491: aload_0
     492: invokevirtual #115                // Method initParams:()V
     495: aload_0
     496: iconst_1
     497: anewarray     #117                // class java/lang/Class
     500: dup
     501: iconst_0
     502: ldc           #119                // class net/malisis/doors/block/CustomDoor
     504: aastore
     505: invokevirtual #123                // Method ensureBlock:([Ljava/lang/Class;)V
     508: return

  public boolean isGui3d();
    Code:
       0: iconst_1
       1: ireturn

  protected void setItem();
    Code:
       0: aload_0
       1: getfield      #135                // Field itemStack:Lnet/minecraft/item/ItemStack;
       4: invokevirtual #141                // Method net/minecraft/item/ItemStack.func_77978_p:()Lnet/minecraft/nbt/NBTTagCompound;
       7: invokestatic  #147                // Method net/malisis/doors/item/CustomDoorItem.readNBT:(Lnet/minecraft/nbt/NBTTagCompound;)Lorg/apache/commons/lang3/tuple/Triple;
      10: astore_1
      11: aload_0
      12: aload_1
      13: invokevirtual #153                // Method org/apache/commons/lang3/tuple/Triple.getLeft:()Ljava/lang/Object;
      16: checkcast     #155                // class net/minecraft/block/state/IBlockState
      19: putfield      #157                // Field frame:Lnet/minecraft/block/state/IBlockState;
      22: aload_0
      23: aload_1
      24: invokevirtual #160                // Method org/apache/commons/lang3/tuple/Triple.getMiddle:()Ljava/lang/Object;
      27: checkcast     #155                // class net/minecraft/block/state/IBlockState
      30: putfield      #162                // Field top:Lnet/minecraft/block/state/IBlockState;
      33: aload_0
      34: aload_1
      35: invokevirtual #165                // Method org/apache/commons/lang3/tuple/Triple.getRight:()Ljava/lang/Object;
      38: checkcast     #155                // class net/minecraft/block/state/IBlockState
      41: putfield      #167                // Field bottom:Lnet/minecraft/block/state/IBlockState;
      44: aload_0
      45: getstatic     #173                // Field net/minecraft/util/EnumFacing.SOUTH:Lnet/minecraft/util/EnumFacing;
      48: putfield      #176                // Field direction:Lnet/minecraft/util/EnumFacing;
      51: aload_0
      52: invokespecial #179                // Method setupParams:()V
      55: return

  protected void setTileEntity();
    Code:
       0: aload_0
       1: invokespecial #185                // Method net/malisis/doors/renderer/DoorRenderer.setTileEntity:()V
       4: aload_0
       5: getfield      #189                // Field tileEntity:Lnet/minecraft/tileentity/TileEntity;
       8: checkcast     #20                 // class net/malisis/doors/tileentity/CustomDoorTileEntity
      11: astore_1
      12: aload_0
      13: aload_1
      14: invokevirtual #193                // Method net/malisis/doors/tileentity/CustomDoorTileEntity.getFrame:()Lnet/minecraft/block/state/IBlockState;
      17: putfield      #157                // Field frame:Lnet/minecraft/block/state/IBlockState;
      20: aload_0
      21: aload_1
      22: invokevirtual #196                // Method net/malisis/doors/tileentity/CustomDoorTileEntity.getTop:()Lnet/minecraft/block/state/IBlockState;
      25: putfield      #162                // Field top:Lnet/minecraft/block/state/IBlockState;
      28: aload_0
      29: aload_1
      30: invokevirtual #199                // Method net/malisis/doors/tileentity/CustomDoorTileEntity.getBottom:()Lnet/minecraft/block/state/IBlockState;
      33: putfield      #167                // Field bottom:Lnet/minecraft/block/state/IBlockState;
      36: aload_0
      37: invokespecial #179                // Method setupParams:()V
      40: return

  private void setupParams();
    Code:
       0: aload_0
       1: getfield      #204                // Field rp:Lnet/malisis/core/renderer/RenderParameters;
       4: getfield      #210                // Field net/malisis/core/renderer/RenderParameters.alpha:Lnet/malisis/core/renderer/Parameter;
       7: invokevirtual #215                // Method net/malisis/core/renderer/Parameter.reset:()V
      10: aload_0
      11: getfield      #204                // Field rp:Lnet/malisis/core/renderer/RenderParameters;
      14: getfield      #218                // Field net/malisis/core/renderer/RenderParameters.icon:Lnet/malisis/core/renderer/Parameter;
      17: aload_0
      18: getfield      #157                // Field frame:Lnet/minecraft/block/state/IBlockState;
      21: invokestatic  #224                // Method net/malisis/core/renderer/icon/Icon.from:(Lnet/minecraft/block/state/IBlockState;)Lnet/malisis/core/renderer/icon/Icon;
      24: invokevirtual #228                // Method net/malisis/core/renderer/Parameter.set:(Ljava/lang/Object;)V
      27: aload_0
      28: getfield      #204                // Field rp:Lnet/malisis/core/renderer/RenderParameters;
      31: getfield      #231                // Field net/malisis/core/renderer/RenderParameters.colorMultiplier:Lnet/malisis/core/renderer/Parameter;
      34: aload_0
      35: aload_0
      36: getfield      #157                // Field frame:Lnet/minecraft/block/state/IBlockState;
      39: invokespecial #235                // Method getColor:(Lnet/minecraft/block/state/IBlockState;)I
      42: invokestatic  #241                // Method java/lang/Integer.valueOf:(I)Ljava/lang/Integer;
      45: invokevirtual #228                // Method net/malisis/core/renderer/Parameter.set:(Ljava/lang/Object;)V
      48: aload_0
      49: getfield      #104                // Field model:Lnet/malisis/core/renderer/model/MalisisModel;
      52: ldc           #110                // String top
      54: invokevirtual #245                // Method net/malisis/core/renderer/model/MalisisModel.getShape:(Ljava/lang/String;)Lnet/malisis/core/renderer/element/Shape;
      57: ldc           #85                 // String frame
      59: aload_0
      60: getfield      #204                // Field rp:Lnet/malisis/core/renderer/RenderParameters;
      63: iconst_1
      64: invokevirtual #249                // Method net/malisis/core/renderer/element/Shape.setParameters:(Ljava/lang/String;Lnet/malisis/core/renderer/RenderParameters;Z)Lnet/malisis/core/renderer/element/Shape;
      67: pop
      68: aload_0
      69: getfield      #104                // Field model:Lnet/malisis/core/renderer/model/MalisisModel;
      72: ldc           #105                // String bottom
      74: invokevirtual #245                // Method net/malisis/core/renderer/model/MalisisModel.getShape:(Ljava/lang/String;)Lnet/malisis/core/renderer/element/Shape;
      77: ldc           #85                 // String frame
      79: aload_0
      80: getfield      #204                // Field rp:Lnet/malisis/core/renderer/RenderParameters;
      83: iconst_1
      84: invokevirtual #249                // Method net/malisis/core/renderer/element/Shape.setParameters:(Ljava/lang/String;Lnet/malisis/core/renderer/RenderParameters;Z)Lnet/malisis/core/renderer/element/Shape;
      87: pop
      88: aload_0
      89: getfield      #204                // Field rp:Lnet/malisis/core/renderer/RenderParameters;
      92: getfield      #218                // Field net/malisis/core/renderer/RenderParameters.icon:Lnet/malisis/core/renderer/Parameter;
      95: aload_0
      96: getfield      #162                // Field top:Lnet/minecraft/block/state/IBlockState;
      99: invokestatic  #224                // Method net/malisis/core/renderer/icon/Icon.from:(Lnet/minecraft/block/state/IBlockState;)Lnet/malisis/core/renderer/icon/Icon;
     102: invokevirtual #228                // Method net/malisis/core/renderer/Parameter.set:(Ljava/lang/Object;)V
     105: aload_0
     106: getfield      #204                // Field rp:Lnet/malisis/core/renderer/RenderParameters;
     109: getfield      #231                // Field net/malisis/core/renderer/RenderParameters.colorMultiplier:Lnet/malisis/core/renderer/Parameter;
     112: aload_0
     113: aload_0
     114: getfield      #162                // Field top:Lnet/minecraft/block/state/IBlockState;
     117: invokespecial #235                // Method getColor:(Lnet/minecraft/block/state/IBlockState;)I
     120: invokestatic  #241                // Method java/lang/Integer.valueOf:(I)Ljava/lang/Integer;
     123: invokevirtual #228                // Method net/malisis/core/renderer/Parameter.set:(Ljava/lang/Object;)V
     126: aload_0
     127: getfield      #104                // Field model:Lnet/malisis/core/renderer/model/MalisisModel;
     130: ldc           #110                // String top
     132: invokevirtual #245                // Method net/malisis/core/renderer/model/MalisisModel.getShape:(Ljava/lang/String;)Lnet/malisis/core/renderer/element/Shape;
     135: ldc           #91                 // String material
     137: aload_0
     138: getfield      #204                // Field rp:Lnet/malisis/core/renderer/RenderParameters;
     141: iconst_1
     142: invokevirtual #249                // Method net/malisis/core/renderer/element/Shape.setParameters:(Ljava/lang/String;Lnet/malisis/core/renderer/RenderParameters;Z)Lnet/malisis/core/renderer/element/Shape;
     145: pop
     146: aload_0
     147: getfield      #204                // Field rp:Lnet/malisis/core/renderer/RenderParameters;
     150: getfield      #218                // Field net/malisis/core/renderer/RenderParameters.icon:Lnet/malisis/core/renderer/Parameter;
     153: aload_0
     154: getfield      #167                // Field bottom:Lnet/minecraft/block/state/IBlockState;
     157: invokestatic  #224                // Method net/malisis/core/renderer/icon/Icon.from:(Lnet/minecraft/block/state/IBlockState;)Lnet/malisis/core/renderer/icon/Icon;
     160: invokevirtual #228                // Method net/malisis/core/renderer/Parameter.set:(Ljava/lang/Object;)V
     163: aload_0
     164: getfield      #204                // Field rp:Lnet/malisis/core/renderer/RenderParameters;
     167: getfield      #231                // Field net/malisis/core/renderer/RenderParameters.colorMultiplier:Lnet/malisis/core/renderer/Parameter;
     170: aload_0
     171: aload_0
     172: getfield      #167                // Field bottom:Lnet/minecraft/block/state/IBlockState;
     175: invokespecial #235                // Method getColor:(Lnet/minecraft/block/state/IBlockState;)I
     178: invokestatic  #241                // Method java/lang/Integer.valueOf:(I)Ljava/lang/Integer;
     181: invokevirtual #228                // Method net/malisis/core/renderer/Parameter.set:(Ljava/lang/Object;)V
     184: aload_0
     185: getfield      #104                // Field model:Lnet/malisis/core/renderer/model/MalisisModel;
     188: ldc           #105                // String bottom
     190: invokevirtual #245                // Method net/malisis/core/renderer/model/MalisisModel.getShape:(Ljava/lang/String;)Lnet/malisis/core/renderer/element/Shape;
     193: ldc           #91                 // String material
     195: aload_0
     196: getfield      #204                // Field rp:Lnet/malisis/core/renderer/RenderParameters;
     199: iconst_1
     200: invokevirtual #249                // Method net/malisis/core/renderer/element/Shape.setParameters:(Ljava/lang/String;Lnet/malisis/core/renderer/RenderParameters;Z)Lnet/malisis/core/renderer/element/Shape;
     203: pop
     204: aload_0
     205: getfield      #204                // Field rp:Lnet/malisis/core/renderer/RenderParameters;
     208: getfield      #218                // Field net/malisis/core/renderer/RenderParameters.icon:Lnet/malisis/core/renderer/Parameter;
     211: invokevirtual #215                // Method net/malisis/core/renderer/Parameter.reset:()V
     214: aload_0
     215: getfield      #204                // Field rp:Lnet/malisis/core/renderer/RenderParameters;
     218: getfield      #231                // Field net/malisis/core/renderer/RenderParameters.colorMultiplier:Lnet/malisis/core/renderer/Parameter;
     221: invokevirtual #215                // Method net/malisis/core/renderer/Parameter.reset:()V
     224: return

  private int getColor(net.minecraft.block.state.IBlockState);
    Code:
       0: aload_1
       1: invokeinterface #253,  1          // InterfaceMethod net/minecraft/block/state/IBlockState.func_177230_c:()Lnet/minecraft/block/Block;
       6: getstatic     #259                // Field net/minecraft/init/Blocks.field_150349_c:Lnet/minecraft/block/BlockGrass;
       9: if_acmpne     16
      12: ldc_w         #260                // int 16777215
      15: ireturn
      16: aload_0
      17: getfield      #264                // Field world:Lnet/minecraft/world/IBlockAccess;
      20: aload_0
      21: getfield      #268                // Field pos:Lnet/minecraft/util/math/BlockPos;
      24: aload_1
      25: invokestatic  #271                // Method colorMultiplier:(Lnet/minecraft/world/IBlockAccess;Lnet/minecraft/util/math/BlockPos;Lnet/minecraft/block/state/IBlockState;)I
      28: ireturn

  static {};
    Code:
       0: new           #2                  // class net/malisis/doors/renderer/CustomDoorRenderer
       3: dup
       4: invokespecial #274                // Method "<init>":()V
       7: putstatic     #276                // Field instance:Lnet/malisis/doors/renderer/CustomDoorRenderer;
      10: return
}
